<?xml version="1.0" encoding="UTF-8"?>
<Root>
  <PM_HEADER>
    <DONE_IRR>true</DONE_IRR>
  </PM_HEADER>
  <PARTIAL_MATRIX>
    <PARTIAL_DYN>
   5.937529612380531E+00   5.543426470610054E-17
   3.210885892870991E-02   2.296511242630395E-04
   4.933911471096668E-03  -4.138818256355427E-03
   9.597764945712167E-02   6.592834054879227E-04
   9.459280749484575E-02  -1.563151163877817E-04
  -9.652368782225185E-03  -3.870588334019032E-03
   3.210885892870969E-02  -2.296511242635865E-04
   5.853679749400068E+00  -2.390438620130587E-16
   1.074961729524816E-01   1.253389510552996E-04
  -1.577245694487782E-02   3.571375755286022E-03
   9.687478499755538E-03   3.203199256470603E-03
   9.453575626971007E-02  -5.670340237472186E-04
   4.933911471096369E-03   4.138818256355288E-03
   1.074961729524813E-01  -1.253389510553534E-04
   7.853560001454483E+00  -9.918001778321056E-17
   1.750583345764813E-03  -7.824622737292248E-03
   2.540971110937059E-02  -5.484510748639255E-03
   9.142196236227672E-02   2.302032373904858E-03
   9.597764945712091E-02  -6.592834054879117E-04
  -1.577245694487802E-02  -3.571375755285939E-03
   1.750583345764758E-03   7.824622737292250E-03
   7.856596169714505E+00  -1.029859248288446E-16
   1.049332677432274E-01   4.566839247208099E-04
  -1.507233152658543E-02   7.896443829424749E-03
   9.459280749484740E-02   1.563151163877981E-04
   9.687478499756758E-03  -3.203199256470604E-03
   2.540971110937058E-02   5.484510748639097E-03
   1.049332677432278E-01  -4.566839247208364E-04
   8.326634174644951E+00  -1.871206265934959E-16
  -2.129803474654588E-02  -1.054698743579051E-02
  -9.652368782224871E-03   3.870588334019034E-03
   9.453575626970903E-02   5.670340237472356E-04
   9.142196236227754E-02  -2.302032373904817E-03
  -1.507233152658570E-02  -7.896443829424515E-03
  -2.129803474654599E-02   1.054698743579113E-02
   8.414866323789761E+00   3.510962682858925E-18
    </PARTIAL_DYN>
  </PARTIAL_MATRIX>
</Root>
